{"words":8175,"items":[{"key":"aar","endIndex":1,"keyWords":1},{"key":"aba","endIndex":4,"keyWords":3},{"key":"abb","endIndex":7,"keyWords":3},{"key":"abd","endIndex":12,"keyWords":5},{"key":"abe","endIndex":13,"keyWords":1},{"key":"abh","endIndex":14,"keyWords":1},{"key":"abi","endIndex":16,"keyWords":2},{"key":"abj","endIndex":17,"keyWords":1},{"key":"abl","endIndex":19,"keyWords":2},{"key":"abn","endIndex":20,"keyWords":1},{"key":"abo","endIndex":28,"keyWords":8},{"key":"abr","endIndex":29,"keyWords":1},{"key":"abs","endIndex":38,"keyWords":9},{"key":"abu","endIndex":41,"keyWords":3},{"key":"aby","endIndex":42,"keyWords":1},{"key":"aca","endIndex":44,"keyWords":2},{"key":"acc","endIndex":59,"keyWords":15},{"key":"ach","endIndex":61,"keyWords":2},{"key":"aci","endIndex":64,"keyWords":3},{"key":"acn","endIndex":65,"keyWords":1},{"key":"aco","endIndex":68,"keyWords":3},{"key":"acq","endIndex":71,"keyWords":3},{"key":"acr","endIndex":73,"keyWords":2},{"key":"act","endIndex":83,"keyWords":10},{"key":"acu","endIndex":85,"keyWords":2},{"key":"ada","endIndex":89,"keyWords":4},{"key":"add","endIndex":96,"keyWords":7},{"key":"ade","endIndex":98,"keyWords":2},{"key":"adh","endIndex":100,"keyWords":2},{"key":"adj","endIndex":103,"keyWords":3},{"key":"adm","endIndex":109,"keyWords":6},{"key":"ado","endIndex":115,"keyWords":6},{"key":"adu","endIndex":118,"keyWords":3},{"key":"adv","endIndex":132,"keyWords":14},{"key":"aer","endIndex":134,"keyWords":2},{"key":"aes","endIndex":135,"keyWords":1},{"key":"aff","endIndex":143,"keyWords":8},{"key":"afr","endIndex":146,"keyWords":3},{"key":"aft","endIndex":148,"keyWords":2},{"key":"aga","endIndex":150,"keyWords":2},{"key":"age","endIndex":153,"keyWords":3},{"key":"agg","endIndex":155,"keyWords":2},{"key":"agh","endIndex":156,"keyWords":1},{"key":"agi","endIndex":160,"keyWords":4},{"key":"agr","endIndex":162,"keyWords":2},{"key":"ahe","endIndex":163,"keyWords":1},{"key":"aid","endIndex":164,"keyWords":1},{"key":"air","endIndex":173,"keyWords":9},{"key":"ais","endIndex":174,"keyWords":1},{"key":"aja","endIndex":175,"keyWords":1},{"key":"ala","endIndex":178,"keyWords":3},{"key":"alb","endIndex":183,"keyWords":5},{"key":"alc","endIndex":185,"keyWords":2},{"key":"ale","endIndex":186,"keyWords":1},{"key":"alg","endIndex":189,"keyWords":3},{"key":"ali","endIndex":195,"keyWords":6},{"key":"alk","endIndex":196,"keyWords":1},{"key":"all","endIndex":214,"keyWords":18},{"key":"alm","endIndex":217,"keyWords":3},{"key":"alo","endIndex":221,"keyWords":4},{"key":"alp","endIndex":223,"keyWords":2},{"key":"alr","endIndex":224,"keyWords":1},{"key":"als","endIndex":225,"keyWords":1},{"key":"alt","endIndex":231,"keyWords":6},{"key":"alw","endIndex":232,"keyWords":1},{"key":"ama","endIndex":237,"keyWords":5},{"key":"amb","endIndex":244,"keyWords":7},{"key":"ame","endIndex":248,"keyWords":4},{"key":"ami","endIndex":249,"keyWords":1},{"key":"amm","endIndex":250,"keyWords":1},{"key":"amn","endIndex":252,"keyWords":2},{"key":"amo","endIndex":257,"keyWords":5},{"key":"amp","endIndex":262,"keyWords":5},{"key":"amu","endIndex":264,"keyWords":2},{"key":"ana","endIndex":274,"keyWords":10},{"key":"anc","endIndex":279,"keyWords":5},{"key":"ane","endIndex":283,"keyWords":4},{"key":"ang","endIndex":290,"keyWords":7},{"key":"ani","endIndex":295,"keyWords":5},{"key":"ank","endIndex":296,"keyWords":1},{"key":"ann","endIndex":304,"keyWords":8},{"key":"ano","endIndex":309,"keyWords":5},{"key":"ans","endIndex":310,"keyWords":1},{"key":"ant","endIndex":320,"keyWords":10},{"key":"anu","endIndex":321,"keyWords":1},{"key":"anv","endIndex":322,"keyWords":1},{"key":"anx","endIndex":324,"keyWords":2},{"key":"any","endIndex":329,"keyWords":5},{"key":"apa","endIndex":333,"keyWords":4},{"key":"ape","endIndex":335,"keyWords":2},{"key":"aph","endIndex":336,"keyWords":1},{"key":"apo","endIndex":339,"keyWords":3},{"key":"app","endIndex":356,"keyWords":17},{"key":"apr","endIndex":359,"keyWords":3},{"key":"apt","endIndex":360,"keyWords":1},{"key":"aqu","endIndex":364,"keyWords":4},{"key":"ara","endIndex":368,"keyWords":4},{"key":"arb","endIndex":370,"keyWords":2},{"key":"arc","endIndex":379,"keyWords":9},{"key":"ard","endIndex":382,"keyWords":3},{"key":"are","endIndex":384,"keyWords":2},{"key":"arg","endIndex":388,"keyWords":4},{"key":"ari","endIndex":392,"keyWords":4},{"key":"ark","endIndex":393,"keyWords":1},{"key":"arm","endIndex":404,"keyWords":11},{"key":"aro","endIndex":408,"keyWords":4},{"key":"arr","endIndex":416,"keyWords":8},{"key":"ars","endIndex":418,"keyWords":2},{"key":"art","endIndex":426,"keyWords":8},{"key":"asb","endIndex":427,"keyWords":1},{"key":"asc","endIndex":430,"keyWords":3},{"key":"ase","endIndex":431,"keyWords":1},{"key":"ash","endIndex":434,"keyWords":3},{"key":"asi","endIndex":437,"keyWords":3},{"key":"asl","endIndex":438,"keyWords":1},{"key":"asp","endIndex":443,"keyWords":5},{"key":"ass","endIndex":457,"keyWords":14},{"key":"ast","endIndex":467,"keyWords":10},{"key":"asy","endIndex":468,"keyWords":1},{"key":"ath","endIndex":471,"keyWords":3},{"key":"atl","endIndex":473,"keyWords":2},{"key":"ato","endIndex":475,"keyWords":2},{"key":"atr","endIndex":476,"keyWords":1},{"key":"att","endIndex":489,"keyWords":13},{"key":"aub","endIndex":490,"keyWords":1},{"key":"auc","endIndex":491,"keyWords":1},{"key":"aud","endIndex":497,"keyWords":6},{"key":"aug","endIndex":499,"keyWords":2},{"key":"aun","endIndex":501,"keyWords":2},{"key":"aur","endIndex":502,"keyWords":1},{"key":"aus","endIndex":507,"keyWords":5},{"key":"aut","endIndex":521,"keyWords":14},{"key":"aux","endIndex":522,"keyWords":1},{"key":"ava","endIndex":525,"keyWords":3},{"key":"ave","endIndex":529,"keyWords":4},{"key":"avi","endIndex":530,"keyWords":1},{"key":"avo","endIndex":533,"keyWords":3},{"key":"awa","endIndex":538,"keyWords":5},{"key":"awe","endIndex":539,"keyWords":1},{"key":"awf","endIndex":540,"keyWords":1},{"key":"awk","endIndex":541,"keyWords":1},{"key":"awn","endIndex":542,"keyWords":1},{"key":"axi","endIndex":544,"keyWords":2},{"key":"azu","endIndex":545,"keyWords":1},{"key":"bab","endIndex":548,"keyWords":3},{"key":"bac","endIndex":559,"keyWords":11},{"key":"bad","endIndex":562,"keyWords":3},{"key":"baf","endIndex":563,"keyWords":1},{"key":"bag","endIndex":564,"keyWords":1},{"key":"bai","endIndex":567,"keyWords":3},{"key":"bak","endIndex":572,"keyWords":5},{"key":"bal","endIndex":584,"keyWords":12},{"key":"bam","endIndex":585,"keyWords":1},{"key":"ban","endIndex":602,"keyWords":17},{"key":"bap","endIndex":603,"keyWords":1},{"key":"bar","endIndex":630,"keyWords":27},{"key":"bas","endIndex":642,"keyWords":12},{"key":"bat","endIndex":655,"keyWords":13},{"key":"bau","endIndex":656,"keyWords":1},{"key":"bay","endIndex":657,"keyWords":1},{"key":"baz","endIndex":659,"keyWords":2},{"key":"bea","endIndex":673,"keyWords":14},{"key":"bec","endIndex":676,"keyWords":3},{"key":"bed","endIndex":681,"keyWords":5},{"key":"bee","endIndex":690,"keyWords":9},{"key":"bef","endIndex":691,"keyWords":1},{"key":"beg","endIndex":694,"keyWords":3},{"key":"beh","endIndex":698,"keyWords":4},{"key":"bei","endIndex":700,"keyWords":2},{"key":"bel","endIndex":715,"keyWords":15},{"key":"ben","endIndex":718,"keyWords":3},{"key":"beq","endIndex":719,"keyWords":1},{"key":"ber","endIndex":723,"keyWords":4},{"key":"bes","endIndex":725,"keyWords":2},{"key":"bet","endIndex":728,"keyWords":3},{"key":"bev","endIndex":729,"keyWords":1},{"key":"bew","endIndex":730,"keyWords":1},{"key":"bib","endIndex":732,"keyWords":2},{"key":"bic","endIndex":735,"keyWords":3},{"key":"bid","endIndex":736,"keyWords":1},{"key":"bik","endIndex":737,"keyWords":1},{"key":"bil","endIndex":745,"keyWords":8},{"key":"bin","endIndex":750,"keyWords":5},{"key":"bio","endIndex":753,"keyWords":3},{"key":"bir","endIndex":758,"keyWords":5},{"key":"bis","endIndex":762,"keyWords":4},{"key":"bit","endIndex":766,"keyWords":4},{"key":"biz","endIndex":767,"keyWords":1},{"key":"bla","endIndex":781,"keyWords":14},{"key":"ble","endIndex":789,"keyWords":8},{"key":"bli","endIndex":796,"keyWords":7},{"key":"blo","endIndex":810,"keyWords":14},{"key":"blu","endIndex":818,"keyWords":8},{"key":"boa","endIndex":824,"keyWords":6},{"key":"bob","endIndex":826,"keyWords":2},{"key":"bod","endIndex":830,"keyWords":4},{"key":"bog","endIndex":831,"keyWords":1},{"key":"boh","endIndex":832,"keyWords":1},{"key":"boi","endIndex":834,"keyWords":2},{"key":"bol","endIndex":837,"keyWords":3},{"key":"bom","endIndex":840,"keyWords":3},{"key":"bon","endIndex":847,"keyWords":7},{"key":"boo","endIndex":864,"keyWords":17},{"key":"bor","endIndex":871,"keyWords":7},{"key":"bos","endIndex":872,"keyWords":1},{"key":"bot","endIndex":878,"keyWords":6},{"key":"bou","endIndex":884,"keyWords":6},{"key":"bow","endIndex":888,"keyWords":4},{"key":"box","endIndex":890,"keyWords":2},{"key":"boy","endIndex":893,"keyWords":3},{"key":"bra","endIndex":916,"keyWords":23},{"key":"bre","endIndex":932,"keyWords":16},{"key":"bri","endIndex":952,"keyWords":20},{"key":"bro","endIndex":971,"keyWords":19},{"key":"bru","endIndex":977,"keyWords":6},{"key":"bub","endIndex":978,"keyWords":1},{"key":"buc","endIndex":981,"keyWords":3},{"key":"bud","endIndex":985,"keyWords":4},{"key":"buf","endIndex":989,"keyWords":4},{"key":"bug","endIndex":990,"keyWords":1},{"key":"bui","endIndex":994,"keyWords":4},{"key":"bul","endIndex":1006,"keyWords":12},{"key":"bum","endIndex":1008,"keyWords":2},{"key":"bun","endIndex":1014,"keyWords":6},{"key":"buo","endIndex":1016,"keyWords":2},{"key":"bur","endIndex":1028,"keyWords":12},{"key":"bus","endIndex":1033,"keyWords":5},{"key":"but","endIndex":1041,"keyWords":8},{"key":"buy","endIndex":1042,"keyWords":1},{"key":"buz","endIndex":1045,"keyWords":3},{"key":"byp","endIndex":1047,"keyWords":2},{"key":"bys","endIndex":1048,"keyWords":1},{"key":"byt","endIndex":1049,"keyWords":1},{"key":"byw","endIndex":1050,"keyWords":1},{"key":"cab","endIndex":1055,"keyWords":5},{"key":"cac","endIndex":1058,"keyWords":3},{"key":"cad","endIndex":1059,"keyWords":1},{"key":"cae","endIndex":1060,"keyWords":1},{"key":"caf","endIndex":1062,"keyWords":2},{"key":"cag","endIndex":1063,"keyWords":1},{"key":"cah","endIndex":1064,"keyWords":1},{"key":"cak","endIndex":1065,"keyWords":1},{"key":"cal","endIndex":1074,"keyWords":9},{"key":"cam","endIndex":1086,"keyWords":12},{"key":"can","endIndex":1109,"keyWords":23},{"key":"cap","endIndex":1123,"keyWords":14},{"key":"car","endIndex":1161,"keyWords":38},{"key":"cas","endIndex":1176,"keyWords":15},{"key":"cat","endIndex":1189,"keyWords":13},{"key":"cau","endIndex":1197,"keyWords":8},{"key":"cav","endIndex":1202,"keyWords":5},{"key":"cea","endIndex":1203,"keyWords":1},{"key":"ced","endIndex":1205,"keyWords":2},{"key":"cei","endIndex":1206,"keyWords":1},{"key":"cel","endIndex":1220,"keyWords":14},{"key":"cem","endIndex":1221,"keyWords":1},{"key":"cen","endIndex":1227,"keyWords":6},{"key":"cer","endIndex":1234,"keyWords":7},{"key":"ces","endIndex":1235,"keyWords":1},{"key":"cey","endIndex":1236,"keyWords":1},{"key":"cha","endIndex":1275,"keyWords":39},{"key":"che","endIndex":1298,"keyWords":23},{"key":"chi","endIndex":1325,"keyWords":27},{"key":"chl","endIndex":1326,"keyWords":1},{"key":"cho","endIndex":1337,"keyWords":11},{"key":"chr","endIndex":1343,"keyWords":6},{"key":"chu","endIndex":1350,"keyWords":7},{"key":"cid","endIndex":1351,"keyWords":1},{"key":"cig","endIndex":1353,"keyWords":2},{"key":"cin","endIndex":1357,"keyWords":4},{"key":"cir","endIndex":1362,"keyWords":5},{"key":"cis","endIndex":1363,"keyWords":1},{"key":"cit","endIndex":1368,"keyWords":5},{"key":"civ","endIndex":1372,"keyWords":4},{"key":"cla","endIndex":1392,"keyWords":20},{"key":"cle","endIndex":1403,"keyWords":11},{"key":"cli","endIndex":1413,"keyWords":10},{"key":"clo","endIndex":1429,"keyWords":16},{"key":"clu","endIndex":1434,"keyWords":5},{"key":"coa","endIndex":1443,"keyWords":9},{"key":"cob","endIndex":1444,"keyWords":1},{"key":"coc","endIndex":1455,"keyWords":11},{"key":"cod","endIndex":1457,"keyWords":2},{"key":"coe","endIndex":1459,"keyWords":2},{"key":"cof","endIndex":1461,"keyWords":2},{"key":"cog","endIndex":1463,"keyWords":2},{"key":"coh","endIndex":1465,"keyWords":2},{"key":"coi","endIndex":1469,"keyWords":4},{"key":"cok","endIndex":1470,"keyWords":1},{"key":"col","endIndex":1495,"keyWords":25},{"key":"com","endIndex":1544,"keyWords":49},{"key":"con","endIndex":1620,"keyWords":76},{"key":"coo","endIndex":1627,"keyWords":7},{"key":"cop","endIndex":1631,"keyWords":4},{"key":"dab","endIndex":1632,"keyWords":1},{"key":"dac","endIndex":1633,"keyWords":1},{"key":"dad","endIndex":1634,"keyWords":1},{"key":"daf","endIndex":1635,"keyWords":1},{"key":"dag","endIndex":1636,"keyWords":1},{"key":"dai","endIndex":1639,"keyWords":3},{"key":"dam","endIndex":1642,"keyWords":3},{"key":"dan","endIndex":1652,"keyWords":10},{"key":"dap","endIndex":1653,"keyWords":1},{"key":"dar","endIndex":1660,"keyWords":7},{"key":"das","endIndex":1662,"keyWords":2},{"key":"dat","endIndex":1665,"keyWords":3},{"key":"dau","endIndex":1666,"keyWords":1},{"key":"daw","endIndex":1668,"keyWords":2},{"key":"day","endIndex":1672,"keyWords":4},{"key":"daz","endIndex":1674,"keyWords":2},{"key":"dea","endIndex":1686,"keyWords":12},{"key":"deb","endIndex":1692,"keyWords":6},{"key":"dec","endIndex":1718,"keyWords":26},{"key":"ded","endIndex":1720,"keyWords":2},{"key":"dee","endIndex":1725,"keyWords":5},{"key":"def","endIndex":1743,"keyWords":18},{"key":"deg","endIndex":1744,"keyWords":1},{"key":"deh","endIndex":1745,"keyWords":1},{"key":"dei","endIndex":1746,"keyWords":1},{"key":"dej","endIndex":1747,"keyWords":1},{"key":"del","endIndex":1760,"keyWords":13},{"key":"dem","endIndex":1768,"keyWords":8},{"key":"den","endIndex":1779,"keyWords":11},{"key":"deo","endIndex":1780,"keyWords":1},{"key":"dep","endIndex":1792,"keyWords":12},{"key":"der","endIndex":1794,"keyWords":2},{"key":"des","endIndex":1816,"keyWords":22},{"key":"det","endIndex":1830,"keyWords":14},{"key":"deu","endIndex":1831,"keyWords":1},{"key":"dev","endIndex":1841,"keyWords":10},{"key":"dex","endIndex":1842,"keyWords":1},{"key":"dia","endIndex":1856,"keyWords":14},{"key":"dic","endIndex":1860,"keyWords":4},{"key":"die","endIndex":1862,"keyWords":2},{"key":"dif","endIndex":1864,"keyWords":2},{"key":"dig","endIndex":1871,"keyWords":7},{"key":"dil","endIndex":1874,"keyWords":3},{"key":"dim","endIndex":1876,"keyWords":2},{"key":"din","endIndex":1882,"keyWords":6},{"key":"dio","endIndex":1883,"keyWords":1},{"key":"dip","endIndex":1887,"keyWords":4},{"key":"dir","endIndex":1895,"keyWords":8},{"key":"dis","endIndex":1955,"keyWords":60},{"key":"dit","endIndex":1956,"keyWords":1},{"key":"div","endIndex":1973,"keyWords":17},{"key":"diz","endIndex":1974,"keyWords":1},{"key":"doc","endIndex":1979,"keyWords":5},{"key":"dod","endIndex":1980,"keyWords":1},{"key":"dog","endIndex":1981,"keyWords":1},{"key":"doi","endIndex":1982,"keyWords":1},{"key":"dol","endIndex":1986,"keyWords":4},{"key":"dom","endIndex":1993,"keyWords":7},{"key":"don","endIndex":1998,"keyWords":5},{"key":"doo","endIndex":2006,"keyWords":8},{"key":"dop","endIndex":2007,"keyWords":1},{"key":"dor","endIndex":2009,"keyWords":2},{"key":"dos","endIndex":2011,"keyWords":2},{"key":"dot","endIndex":2012,"keyWords":1},{"key":"dou","endIndex":2016,"keyWords":4},{"key":"dov","endIndex":2017,"keyWords":1},{"key":"dow","endIndex":2024,"keyWords":7},{"key":"doz","endIndex":2026,"keyWords":2},{"key":"dra","endIndex":2037,"keyWords":11},{"key":"dre","endIndex":2045,"keyWords":8},{"key":"dri","endIndex":2057,"keyWords":12},{"key":"dro","endIndex":2065,"keyWords":8},{"key":"dru","endIndex":2071,"keyWords":6},{"key":"dry","endIndex":2072,"keyWords":1},{"key":"dua","endIndex":2073,"keyWords":1},{"key":"dub","endIndex":2074,"keyWords":1},{"key":"duc","endIndex":2077,"keyWords":3},{"key":"due","endIndex":2079,"keyWords":2},{"key":"duf","endIndex":2080,"keyWords":1},{"key":"duk","endIndex":2081,"keyWords":1},{"key":"dul","endIndex":2082,"keyWords":1},{"key":"dum","endIndex":2087,"keyWords":5},{"key":"dun","endIndex":2090,"keyWords":3},{"key":"dup","endIndex":2092,"keyWords":2},{"key":"dur","endIndex":2095,"keyWords":3},{"key":"dus","endIndex":2101,"keyWords":6},{"key":"dut","endIndex":2104,"keyWords":3},{"key":"duv","endIndex":2105,"keyWords":1},{"key":"dwa","endIndex":2106,"keyWords":1},{"key":"dwe","endIndex":2108,"keyWords":2},{"key":"dwi","endIndex":2109,"keyWords":1},{"key":"dyi","endIndex":2110,"keyWords":1},{"key":"dyk","endIndex":2111,"keyWords":1},{"key":"dyn","endIndex":2115,"keyWords":4},{"key":"dys","endIndex":2116,"keyWords":1},{"key":"eac","endIndex":2117,"keyWords":1},{"key":"eag","endIndex":2118,"keyWords":1},{"key":"ear","endIndex":2128,"keyWords":10},{"key":"eas","endIndex":2134,"keyWords":6},{"key":"eav","endIndex":2136,"keyWords":2},{"key":"ebo","endIndex":2137,"keyWords":1},{"key":"ecc","endIndex":2138,"keyWords":1},{"key":"ech","endIndex":2139,"keyWords":1},{"key":"ecl","endIndex":2140,"keyWords":1},{"key":"eco","endIndex":2146,"keyWords":6},{"key":"ecs","endIndex":2147,"keyWords":1},{"key":"ecu","endIndex":2148,"keyWords":1},{"key":"ecz","endIndex":2149,"keyWords":1},{"key":"edd","endIndex":2150,"keyWords":1},{"key":"edg","endIndex":2151,"keyWords":1},{"key":"edi","endIndex":2158,"keyWords":7},{"key":"edu","endIndex":2161,"keyWords":3},{"key":"eer","endIndex":2162,"keyWords":1},{"key":"eff","endIndex":2166,"keyWords":4},{"key":"egg","endIndex":2168,"keyWords":2},{"key":"ego","endIndex":2169,"keyWords":1},{"key":"egy","endIndex":2171,"keyWords":2},{"key":"eig","endIndex":2176,"keyWords":5},{"key":"eir","endIndex":2177,"keyWords":1},{"key":"eit","endIndex":2178,"keyWords":1},{"key":"eje","endIndex":2179,"keyWords":1},{"key":"ela","endIndex":2181,"keyWords":2},{"key":"elb","endIndex":2182,"keyWords":1},{"key":"eld","endIndex":2184,"keyWords":2},{"key":"ele","endIndex":2198,"keyWords":14},{"key":"eli","endIndex":2204,"keyWords":6},{"key":"ell","endIndex":2206,"keyWords":2},{"key":"elo","endIndex":2209,"keyWords":3},{"key":"els","endIndex":2210,"keyWords":1},{"key":"ema","endIndex":2211,"keyWords":1},{"key":"emb","endIndex":2222,"keyWords":11},{"key":"eme","endIndex":2225,"keyWords":3},{"key":"emi","endIndex":2230,"keyWords":5},{"key":"emo","endIndex":2232,"keyWords":2},{"key":"emp","endIndex":2245,"keyWords":13},{"key":"ena","endIndex":2246,"keyWords":1},{"key":"enc","endIndex":2252,"keyWords":6},{"key":"end","endIndex":2259,"keyWords":7},{"key":"ene","endIndex":2262,"keyWords":3},{"key":"eng","endIndex":2269,"keyWords":7},{"key":"eni","endIndex":2271,"keyWords":2},{"key":"enj","endIndex":2274,"keyWords":3},{"key":"enl","endIndex":2275,"keyWords":1},{"key":"enm","endIndex":2276,"keyWords":1},{"key":"eno","endIndex":2278,"keyWords":2},{"key":"enr","endIndex":2281,"keyWords":3},{"key":"ens","endIndex":2284,"keyWords":3},{"key":"ent","endIndex":2291,"keyWords":7},{"key":"enu","endIndex":2292,"keyWords":1},{"key":"env","endIndex":2297,"keyWords":5},{"key":"eph","endIndex":2298,"keyWords":1},{"key":"epi","endIndex":2306,"keyWords":8},{"key":"epo","endIndex":2307,"keyWords":1},{"key":"equ","endIndex":2317,"keyWords":10},{"key":"era","endIndex":2320,"keyWords":3},{"key":"ere","endIndex":2321,"keyWords":1},{"key":"ero","endIndex":2324,"keyWords":3},{"key":"err","endIndex":2326,"keyWords":2},{"key":"eru","endIndex":2328,"keyWords":2},{"key":"esc","endIndex":2332,"keyWords":4},{"key":"eso","endIndex":2333,"keyWords":1},{"key":"esp","endIndex":2334,"keyWords":1},{"key":"ess","endIndex":2337,"keyWords":3},{"key":"est","endIndex":2343,"keyWords":6},{"key":"ete","endIndex":2345,"keyWords":2},{"key":"eth","endIndex":2350,"keyWords":5},{"key":"eti","endIndex":2351,"keyWords":1},{"key":"eul","endIndex":2352,"keyWords":1},{"key":"eun","endIndex":2353,"keyWords":1},{"key":"eup","endIndex":2355,"keyWords":2},{"key":"eur","endIndex":2357,"keyWords":2},{"key":"eva","endIndex":2360,"keyWords":3},{"key":"eve","endIndex":2369,"keyWords":9},{"key":"evi","endIndex":2373,"keyWords":4},{"key":"evo","endIndex":2375,"keyWords":2},{"key":"exa","endIndex":2380,"keyWords":5},{"key":"exc","endIndex":2398,"keyWords":18},{"key":"exe","endIndex":2403,"keyWords":5},{"key":"exh","endIndex":2407,"keyWords":4},{"key":"exi","endIndex":2411,"keyWords":4},{"key":"exo","endIndex":2414,"keyWords":3},{"key":"exp","endIndex":2438,"keyWords":24},{"key":"exq","endIndex":2439,"keyWords":1},{"key":"ext","endIndex":2452,"keyWords":13},{"key":"exu","endIndex":2453,"keyWords":1},{"key":"eye","endIndex":2459,"keyWords":6},{"key":"fab","endIndex":2462,"keyWords":3},{"key":"fac","endIndex":2476,"keyWords":14},{"key":"fai","endIndex":2483,"keyWords":7},{"key":"fak","endIndex":2484,"keyWords":1},{"key":"fal","endIndex":2491,"keyWords":7},{"key":"fam","endIndex":2497,"keyWords":6},{"key":"fan","endIndex":2501,"keyWords":4},{"key":"far","endIndex":2508,"keyWords":7},{"key":"fas","endIndex":2513,"keyWords":5},{"key":"fat","endIndex":2522,"keyWords":9},{"key":"fau","endIndex":2525,"keyWords":3},{"key":"fav","endIndex":2527,"keyWords":2},{"key":"faw","endIndex":2528,"keyWords":1},{"key":"fea","endIndex":2535,"keyWords":7},{"key":"feb","endIndex":2536,"keyWords":1},{"key":"fec","endIndex":2537,"keyWords":1},{"key":"fed","endIndex":2538,"keyWords":1},{"key":"fee","endIndex":2543,"keyWords":5},{"key":"fei","endIndex":2545,"keyWords":2},{"key":"fel","endIndex":2549,"keyWords":4},{"key":"fem","endIndex":2553,"keyWords":4},{"key":"fen","endIndex":2555,"keyWords":2},{"key":"fer","endIndex":2562,"keyWords":7},{"key":"fes","endIndex":2564,"keyWords":2},{"key":"fet","endIndex":2567,"keyWords":3},{"key":"feu","endIndex":2569,"keyWords":2},{"key":"fev","endIndex":2570,"keyWords":1},{"key":"fia","endIndex":2571,"keyWords":1},{"key":"fib","endIndex":2572,"keyWords":1},{"key":"fic","endIndex":2574,"keyWords":2},{"key":"fid","endIndex":2575,"keyWords":1},{"key":"fie","endIndex":2578,"keyWords":3},{"key":"fif","endIndex":2582,"keyWords":4},{"key":"fig","endIndex":2585,"keyWords":3},{"key":"fil","endIndex":2595,"keyWords":10},{"key":"fin","endIndex":2609,"keyWords":14},{"key":"fir","endIndex":2618,"keyWords":9},{"key":"fis","endIndex":2627,"keyWords":9},{"key":"fit","endIndex":2628,"keyWords":1},{"key":"fiv","endIndex":2629,"keyWords":1},{"key":"fix","endIndex":2631,"keyWords":2},{"key":"fla","endIndex":2654,"keyWords":23},{"key":"fle","endIndex":2662,"keyWords":8},{"key":"fli","endIndex":2670,"keyWords":8},{"key":"flo","endIndex":2689,"keyWords":19},{"key":"flu","endIndex":2699,"keyWords":10},{"key":"fly","endIndex":2701,"keyWords":2},{"key":"foa","endIndex":2703,"keyWords":2},{"key":"foc","endIndex":2705,"keyWords":2},{"key":"fod","endIndex":2706,"keyWords":1},{"key":"foi","endIndex":2707,"keyWords":1},{"key":"fol","endIndex":2717,"keyWords":10},{"key":"fon","endIndex":2720,"keyWords":3},{"key":"foo","endIndex":2729,"keyWords":9},{"key":"for","endIndex":2775,"keyWords":46},{"key":"fos","endIndex":2778,"keyWords":3},{"key":"fou","endIndex":2786,"keyWords":8},{"key":"fra","endIndex":2802,"keyWords":16},{"key":"fre","endIndex":2823,"keyWords":21},{"key":"fri","endIndex":2832,"keyWords":9},{"key":"fro","endIndex":2840,"keyWords":8},{"key":"fru","endIndex":2844,"keyWords":4},{"key":"fry","endIndex":2845,"keyWords":1},{"key":"fud","endIndex":2846,"keyWords":1},{"key":"fue","endIndex":2847,"keyWords":1},{"key":"fug","endIndex":2848,"keyWords":1},{"key":"ful","endIndex":2850,"keyWords":2},{"key":"fum","endIndex":2851,"keyWords":1},{"key":"fun","endIndex":2859,"keyWords":8},{"key":"fur","endIndex":2864,"keyWords":5},{"key":"fus","endIndex":2868,"keyWords":4},{"key":"fut","endIndex":2870,"keyWords":2},{"key":"fuz","endIndex":2871,"keyWords":1},{"key":"gad","endIndex":2872,"keyWords":1},{"key":"gaf","endIndex":2873,"keyWords":1},{"key":"gai","endIndex":2876,"keyWords":3},{"key":"gal","endIndex":2887,"keyWords":11},{"key":"gam","endIndex":2893,"keyWords":6},{"key":"gan","endIndex":2898,"keyWords":5},{"key":"gar","endIndex":2908,"keyWords":10},{"key":"gas","endIndex":2912,"keyWords":4},{"key":"gat","endIndex":2916,"keyWords":4},{"key":"gau","endIndex":2920,"keyWords":4},{"key":"gaw","endIndex":2921,"keyWords":1},{"key":"gaz","endIndex":2922,"keyWords":1},{"key":"gea","endIndex":2924,"keyWords":2},{"key":"gem","endIndex":2925,"keyWords":1},{"key":"gen","endIndex":2941,"keyWords":16},{"key":"geo","endIndex":2948,"keyWords":7},{"key":"ger","endIndex":2951,"keyWords":3},{"key":"ges","endIndex":2952,"keyWords":1},{"key":"gey","endIndex":2953,"keyWords":1},{"key":"ghe","endIndex":2954,"keyWords":1},{"key":"gho","endIndex":2955,"keyWords":1},{"key":"gia","endIndex":2956,"keyWords":1},{"key":"gib","endIndex":2957,"keyWords":1},{"key":"gid","endIndex":2958,"keyWords":1},{"key":"gif","endIndex":2959,"keyWords":1},{"key":"gig","endIndex":2961,"keyWords":2},{"key":"gil","endIndex":2963,"keyWords":2},{"key":"gim","endIndex":2964,"keyWords":1},{"key":"gin","endIndex":2965,"keyWords":1},{"key":"gir","endIndex":2970,"keyWords":5},{"key":"gis","endIndex":2971,"keyWords":1},{"key":"giv","endIndex":2972,"keyWords":1},{"key":"gla","endIndex":2983,"keyWords":11},{"key":"gli","endIndex":2988,"keyWords":5},{"key":"glo","endIndex":2999,"keyWords":11},{"key":"glu","endIndex":3005,"keyWords":6},{"key":"gly","endIndex":3006,"keyWords":1},{"key":"gna","endIndex":3009,"keyWords":3},{"key":"gno","endIndex":3010,"keyWords":1},{"key":"goa","endIndex":3013,"keyWords":3},{"key":"gob","endIndex":3014,"keyWords":1},{"key":"god","endIndex":3018,"keyWords":4},{"key":"gol","endIndex":3023,"keyWords":5},{"key":"gon","endIndex":3024,"keyWords":1},{"key":"goo","endIndex":3028,"keyWords":4},{"key":"gor","endIndex":3030,"keyWords":2},{"key":"gos","endIndex":3033,"keyWords":3},{"key":"got","endIndex":3034,"keyWords":1},{"key":"gou","endIndex":3037,"keyWords":3},{"key":"gov","endIndex":3039,"keyWords":2},{"key":"gra","endIndex":3075,"keyWords":36},{"key":"gre","endIndex":3087,"keyWords":12},{"key":"gri","endIndex":3096,"keyWords":9},{"key":"gro","endIndex":3109,"keyWords":13},{"key":"gru","endIndex":3113,"keyWords":4},{"key":"gua","endIndex":3116,"keyWords":3},{"key":"gue","endIndex":3119,"keyWords":3},{"key":"guf","endIndex":3120,"keyWords":1},{"key":"gui","endIndex":3127,"keyWords":7},{"key":"gul","endIndex":3131,"keyWords":4},{"key":"gun","endIndex":3137,"keyWords":6},{"key":"gur","endIndex":3138,"keyWords":1},{"key":"gus","endIndex":3139,"keyWords":1},{"key":"gut","endIndex":3140,"keyWords":1},{"key":"guz","endIndex":3141,"keyWords":1},{"key":"gym","endIndex":3143,"keyWords":2},{"key":"gyp","endIndex":3144,"keyWords":1},{"key":"hab","endIndex":3146,"keyWords":2},{"key":"hac","endIndex":3148,"keyWords":2},{"key":"had","endIndex":3149,"keyWords":1},{"key":"hag","endIndex":3151,"keyWords":2},{"key":"hai","endIndex":3161,"keyWords":10},{"key":"hal","endIndex":3169,"keyWords":8},{"key":"ham","endIndex":3174,"keyWords":5},{"key":"han","endIndex":3195,"keyWords":21},{"key":"hap","endIndex":3198,"keyWords":3},{"key":"har","endIndex":3214,"keyWords":16},{"key":"has","endIndex":3217,"keyWords":3},{"key":"hat","endIndex":3222,"keyWords":5},{"key":"hau","endIndex":3225,"keyWords":3},{"key":"hav","endIndex":3226,"keyWords":1},{"key":"haw","endIndex":3230,"keyWords":4},{"key":"hay","endIndex":3231,"keyWords":1},{"key":"haz","endIndex":3236,"keyWords":5},{"key":"hea","endIndex":3265,"keyWords":29},{"key":"heb","endIndex":3266,"keyWords":1},{"key":"hed","endIndex":3268,"keyWords":2},{"key":"hee","endIndex":3269,"keyWords":1},{"key":"hei","endIndex":3273,"keyWords":4},{"key":"hel","endIndex":3281,"keyWords":8},{"key":"hem","endIndex":3282,"keyWords":1},{"key":"hen","endIndex":3283,"keyWords":1},{"key":"her","endIndex":3302,"keyWords":19},{"key":"hes","endIndex":3303,"keyWords":1},{"key":"hex","endIndex":3304,"keyWords":1},{"key":"hey","endIndex":3305,"keyWords":1},{"key":"hia","endIndex":3306,"keyWords":1},{"key":"hib","endIndex":3307,"keyWords":1},{"key":"hic","endIndex":3308,"keyWords":1},{"key":"hid","endIndex":3309,"keyWords":1},{"key":"hie","endIndex":3310,"keyWords":1},{"key":"hig","endIndex":3314,"keyWords":4},{"key":"hij","endIndex":3315,"keyWords":1},{"key":"hik","endIndex":3316,"keyWords":1},{"key":"hil","endIndex":3320,"keyWords":4},{"key":"him","endIndex":3322,"keyWords":2},{"key":"hin","endIndex":3328,"keyWords":6},{"key":"hip","endIndex":3329,"keyWords":1},{"key":"hir","endIndex":3330,"keyWords":1},{"key":"his","endIndex":3333,"keyWords":3},{"key":"hit","endIndex":3335,"keyWords":2},{"key":"hoa","endIndex":3337,"keyWords":2},{"key":"hob","endIndex":3339,"keyWords":2},{"key":"hoc","endIndex":3340,"keyWords":1},{"key":"hoi","endIndex":3341,"keyWords":1},{"key":"hol","endIndex":3350,"keyWords":9},{"key":"hom","endIndex":3358,"keyWords":8},{"key":"hon","endIndex":3369,"keyWords":11},{"key":"hoo","endIndex":3375,"keyWords":6},{"key":"hop","endIndex":3378,"keyWords":3},{"key":"hor","endIndex":3392,"keyWords":14},{"key":"hos","endIndex":3400,"keyWords":8},{"key":"hot","endIndex":3404,"keyWords":4},{"key":"hou","endIndex":3411,"keyWords":7},{"key":"hov","endIndex":3412,"keyWords":1},{"key":"how","endIndex":3414,"keyWords":2},{"key":"hub","endIndex":3416,"keyWords":2},{"key":"hug","endIndex":3417,"keyWords":1},{"key":"hul","endIndex":3418,"keyWords":1},{"key":"hum","endIndex":3430,"keyWords":12},{"key":"hun","endIndex":3438,"keyWords":8},{"key":"hur","endIndex":3444,"keyWords":6},{"key":"hus","endIndex":3448,"keyWords":4},{"key":"hya","endIndex":3449,"keyWords":1},{"key":"hyb","endIndex":3450,"keyWords":1},{"key":"hyd","endIndex":3452,"keyWords":2},{"key":"hye","endIndex":3453,"keyWords":1},{"key":"hyg","endIndex":3454,"keyWords":1},{"key":"hym","endIndex":3455,"keyWords":1},{"key":"hyp","endIndex":3459,"keyWords":4},{"key":"hys","endIndex":3460,"keyWords":1},{"key":"ibe","endIndex":3461,"keyWords":1},{"key":"icb","endIndex":3462,"keyWords":1},{"key":"ice","endIndex":3465,"keyWords":3},{"key":"ici","endIndex":3467,"keyWords":2},{"key":"ico","endIndex":3468,"keyWords":1},{"key":"ida","endIndex":3469,"keyWords":1},{"key":"ide","endIndex":3475,"keyWords":6},{"key":"idi","endIndex":3479,"keyWords":4},{"key":"idl","endIndex":3480,"keyWords":1},{"key":"ido","endIndex":3482,"keyWords":2},{"key":"igl","endIndex":3483,"keyWords":1},{"key":"ign","endIndex":3489,"keyWords":6},{"key":"ill","endIndex":3495,"keyWords":6},{"key":"ima","endIndex":3499,"keyWords":4},{"key":"imb","endIndex":3500,"keyWords":1},{"key":"imi","endIndex":3504,"keyWords":4},{"key":"imm","endIndex":3514,"keyWords":10},{"key":"imp","endIndex":3535,"keyWords":21},{"key":"ina","endIndex":3538,"keyWords":3},{"key":"inc","endIndex":3554,"keyWords":16},{"key":"ind","endIndex":3569,"keyWords":15},{"key":"ine","endIndex":3573,"keyWords":4},{"key":"inf","endIndex":3598,"keyWords":25},{"key":"ing","endIndex":3599,"keyWords":1},{"key":"inh","endIndex":3604,"keyWords":5},{"key":"ini","endIndex":3606,"keyWords":2},{"key":"inj","endIndex":3611,"keyWords":5},{"key":"ink","endIndex":3612,"keyWords":1},{"key":"inl","endIndex":3614,"keyWords":2},{"key":"inn","endIndex":3620,"keyWords":6},{"key":"ino","endIndex":3621,"keyWords":1},{"key":"inp","endIndex":3622,"keyWords":1},{"key":"inq","endIndex":3624,"keyWords":2},{"key":"ins","endIndex":3645,"keyWords":21},{"key":"int","endIndex":3680,"keyWords":35},{"key":"inv","endIndex":3694,"keyWords":14},{"key":"iod","endIndex":3695,"keyWords":1},{"key":"iot","endIndex":3696,"keyWords":1},{"key":"iow","endIndex":3697,"keyWords":1},{"key":"ira","endIndex":3701,"keyWords":4},{"key":"ire","endIndex":3702,"keyWords":1},{"key":"iri","endIndex":3705,"keyWords":3},{"key":"iro","endIndex":3710,"keyWords":5},{"key":"irr","endIndex":3712,"keyWords":2},{"key":"isl","endIndex":3717,"keyWords":5},{"key":"iso","endIndex":3719,"keyWords":2},{"key":"isr","endIndex":3721,"keyWords":2},{"key":"ist","endIndex":3722,"keyWords":1},{"key":"ita","endIndex":3724,"keyWords":2},{"key":"itc","endIndex":3726,"keyWords":2},{"key":"ite","endIndex":3727,"keyWords":1},{"key":"iti","endIndex":3729,"keyWords":2},{"key":"its","endIndex":3730,"keyWords":1},{"key":"ivo","endIndex":3731,"keyWords":1},{"key":"jab","endIndex":3732,"keyWords":1},{"key":"jac","endIndex":3735,"keyWords":3},{"key":"jad","endIndex":3736,"keyWords":1},{"key":"jag","endIndex":3737,"keyWords":1},{"key":"jam","endIndex":3738,"keyWords":1},{"key":"jan","endIndex":3740,"keyWords":2},{"key":"jap","endIndex":3742,"keyWords":2},{"key":"jar","endIndex":3743,"keyWords":1},{"key":"jau","endIndex":3744,"keyWords":1},{"key":"jav","endIndex":3745,"keyWords":1},{"key":"jaz","endIndex":3746,"keyWords":1},{"key":"jea","endIndex":3749,"keyWords":3},{"key":"jee","endIndex":3750,"keyWords":1},{"key":"jel","endIndex":3752,"keyWords":2},{"key":"jeo","endIndex":3753,"keyWords":1},{"key":"jer","endIndex":3756,"keyWords":3},{"key":"jet","endIndex":3757,"keyWords":1},{"key":"jew","endIndex":3762,"keyWords":5},{"key":"jig","endIndex":3763,"keyWords":1},{"key":"jil","endIndex":3764,"keyWords":1},{"key":"jin","endIndex":3766,"keyWords":2},{"key":"joc","endIndex":3768,"keyWords":2},{"key":"joi","endIndex":3771,"keyWords":3},{"key":"jok","endIndex":3773,"keyWords":2},{"key":"jol","endIndex":3774,"keyWords":1},{"key":"jor","endIndex":3775,"keyWords":1},{"key":"jos","endIndex":3776,"keyWords":1},{"key":"jou","endIndex":3778,"keyWords":2},{"key":"joy","endIndex":3780,"keyWords":2},{"key":"jub","endIndex":3781,"keyWords":1},{"key":"jud","endIndex":3786,"keyWords":5},{"key":"jug","endIndex":3788,"keyWords":2},{"key":"jui","endIndex":3789,"keyWords":1},{"key":"juk","endIndex":3790,"keyWords":1},{"key":"jul","endIndex":3791,"keyWords":1},{"key":"jum","endIndex":3794,"keyWords":3},{"key":"jun","endIndex":3798,"keyWords":4},{"key":"jur","endIndex":3800,"keyWords":2},{"key":"jus","endIndex":3802,"keyWords":2},{"key":"juv","endIndex":3803,"keyWords":1},{"key":"kan","endIndex":3805,"keyWords":2},{"key":"kar","endIndex":3806,"keyWords":1},{"key":"kee","endIndex":3808,"keyWords":2},{"key":"ken","endIndex":3811,"keyWords":3},{"key":"ker","endIndex":3814,"keyWords":3},{"key":"ket","endIndex":3816,"keyWords":2},{"key":"key","endIndex":3819,"keyWords":3},{"key":"kha","endIndex":3820,"keyWords":1},{"key":"kic","endIndex":3821,"keyWords":1},{"key":"kid","endIndex":3823,"keyWords":2},{"key":"kil","endIndex":3831,"keyWords":8},{"key":"kin","endIndex":3836,"keyWords":5},{"key":"kio","endIndex":3837,"keyWords":1},{"key":"kis","endIndex":3838,"keyWords":1},{"key":"kit","endIndex":3842,"keyWords":4},{"key":"kiw","endIndex":3843,"keyWords":1},{"key":"kna","endIndex":3845,"keyWords":2},{"key":"kne","endIndex":3848,"keyWords":3},{"key":"kni","endIndex":3852,"keyWords":4},{"key":"kno","endIndex":3857,"keyWords":5},{"key":"knu","endIndex":3858,"keyWords":1},{"key":"kor","endIndex":3860,"keyWords":2},{"key":"kos","endIndex":3861,"keyWords":1},{"key":"kud","endIndex":3862,"keyWords":1},{"key":"kuw","endIndex":3863,"keyWords":1},{"key":"lab","endIndex":3867,"keyWords":4},{"key":"lac","endIndex":3872,"keyWords":5},{"key":"lad","endIndex":3876,"keyWords":4},{"key":"lag","endIndex":3877,"keyWords":1},{"key":"lai","endIndex":3878,"keyWords":1},{"key":"lak","endIndex":3879,"keyWords":1},{"key":"lam","endIndex":3885,"keyWords":6},{"key":"lan","endIndex":3894,"keyWords":9},{"key":"lap","endIndex":3895,"keyWords":1},{"key":"lar","endIndex":3900,"keyWords":5},{"key":"las","endIndex":3902,"keyWords":2},{"key":"lat","endIndex":3911,"keyWords":9},{"key":"lau","endIndex":3918,"keyWords":7},{"key":"lav","endIndex":3920,"keyWords":2},{"key":"law","endIndex":3925,"keyWords":5},{"key":"lax","endIndex":3926,"keyWords":1},{"key":"lay","endIndex":3930,"keyWords":4},{"key":"laz","endIndex":3931,"keyWords":1},{"key":"lea","endIndex":3948,"keyWords":17},{"key":"leb","endIndex":3950,"keyWords":2},{"key":"lec","endIndex":3952,"keyWords":2},{"key":"led","endIndex":3953,"keyWords":1},{"key":"lee","endIndex":3956,"keyWords":3},{"key":"lef","endIndex":3959,"keyWords":3},{"key":"leg","endIndex":3967,"keyWords":8},{"key":"lei","endIndex":3969,"keyWords":2},{"key":"lem","endIndex":3971,"keyWords":2},{"key":"len","endIndex":3977,"keyWords":6},{"key":"leo","endIndex":3979,"keyWords":2},{"key":"lep","endIndex":3981,"keyWords":2},{"key":"les","endIndex":3986,"keyWords":5},{"key":"let","endIndex":3990,"keyWords":4},{"key":"leu","endIndex":3991,"keyWords":1},{"key":"lev","endIndex":3994,"keyWords":3},{"key":"lew","endIndex":3995,"keyWords":1},{"key":"lia","endIndex":3998,"keyWords":3},{"key":"lib","endIndex":4004,"keyWords":6},{"key":"lic","endIndex":4007,"keyWords":3},{"key":"lif","endIndex":4013,"keyWords":6},{"key":"lig","endIndex":4017,"keyWords":4},{"key":"lik","endIndex":4022,"keyWords":5},{"key":"lil","endIndex":4024,"keyWords":2},{"key":"lim","endIndex":4032,"keyWords":8},{"key":"lin","endIndex":4039,"keyWords":7},{"key":"lio","endIndex":4041,"keyWords":2},{"key":"lip","endIndex":4042,"keyWords":1},{"key":"liq","endIndex":4047,"keyWords":5},{"key":"lis","endIndex":4052,"keyWords":5},{"key":"lit","endIndex":4059,"keyWords":7},{"key":"liv","endIndex":4063,"keyWords":4},{"key":"liz","endIndex":4064,"keyWords":1},{"key":"lla","endIndex":4065,"keyWords":1},{"key":"loa","endIndex":4069,"keyWords":4},{"key":"lob","endIndex":4071,"keyWords":2},{"key":"loc","endIndex":4078,"keyWords":7},{"key":"lod","endIndex":4080,"keyWords":2},{"key":"lof","endIndex":4081,"keyWords":1},{"key":"log","endIndex":4083,"keyWords":2},{"key":"lol","endIndex":4084,"keyWords":1},{"key":"lon","endIndex":4093,"keyWords":9},{"key":"loo","endIndex":4098,"keyWords":5},{"key":"lor","endIndex":4099,"keyWords":1},{"key":"los","endIndex":4102,"keyWords":3},{"key":"lot","endIndex":4104,"keyWords":2},{"key":"lou","endIndex":4108,"keyWords":4},{"key":"lov","endIndex":4112,"keyWords":4},{"key":"low","endIndex":4113,"keyWords":1},{"key":"loy","endIndex":4115,"keyWords":2},{"key":"loz","endIndex":4116,"keyWords":1},{"key":"lub","endIndex":4117,"keyWords":1},{"key":"luc","endIndex":4121,"keyWords":4},{"key":"lug","endIndex":4122,"keyWords":1},{"key":"luk","endIndex":4123,"keyWords":1},{"key":"lul","endIndex":4124,"keyWords":1},{"key":"lum","endIndex":4127,"keyWords":3},{"key":"lun","endIndex":4131,"keyWords":4},{"key":"lur","endIndex":4133,"keyWords":2},{"key":"lus","endIndex":4134,"keyWords":1},{"key":"lut","endIndex":4135,"keyWords":1},{"key":"lux","endIndex":4138,"keyWords":3},{"key":"lyn","endIndex":4140,"keyWords":2},{"key":"lyr","endIndex":4143,"keyWords":3},{"key":"mac","endIndex":4150,"keyWords":7},{"key":"mad","endIndex":4155,"keyWords":5},{"key":"mag","endIndex":4166,"keyWords":11},{"key":"mah","endIndex":4167,"keyWords":1},{"key":"mai","endIndex":4178,"keyWords":11},{"key":"maj","endIndex":4181,"keyWords":3},{"key":"mak","endIndex":4184,"keyWords":3},{"key":"mal","endIndex":4197,"keyWords":13},{"key":"mam","endIndex":4199,"keyWords":2},{"key":"man","endIndex":4227,"keyWords":28},{"key":"map","endIndex":4228,"keyWords":1},{"key":"mar","endIndex":4261,"keyWords":33},{"key":"mas","endIndex":4273,"keyWords":12},{"key":"mat","endIndex":4287,"keyWords":14},{"key":"mau","endIndex":4291,"keyWords":4},{"key":"max","endIndex":4294,"keyWords":3},{"key":"may","endIndex":4296,"keyWords":2},{"key":"maz","endIndex":4297,"keyWords":1},{"key":"mea","endIndex":4309,"keyWords":12},{"key":"mec","endIndex":4313,"keyWords":4},{"key":"med","endIndex":4324,"keyWords":11},{"key":"mee","endIndex":4326,"keyWords":2},{"key":"meg","endIndex":4327,"keyWords":1},{"key":"mel","endIndex":4332,"keyWords":5},{"key":"mem","endIndex":4339,"keyWords":7},{"key":"men","endIndex":4349,"keyWords":10},{"key":"mer","endIndex":4363,"keyWords":14},{"key":"mes","endIndex":4368,"keyWords":5},{"key":"met","endIndex":4378,"keyWords":10},{"key":"mex","endIndex":4380,"keyWords":2},{"key":"mic","endIndex":4385,"keyWords":5},{"key":"mid","endIndex":4393,"keyWords":8},{"key":"mig","endIndex":4397,"keyWords":4},{"key":"mil","endIndex":4413,"keyWords":16},{"key":"mim","endIndex":4414,"keyWords":1},{"key":"min","endIndex":4438,"keyWords":24},{"key":"mir","endIndex":4442,"keyWords":4},{"key":"mis","endIndex":4461,"keyWords":19},{"key":"mit","endIndex":4464,"keyWords":3},{"key":"mix","endIndex":4466,"keyWords":2},{"key":"moa","endIndex":4468,"keyWords":2},{"key":"mob","endIndex":4470,"keyWords":2},{"key":"moc","endIndex":4472,"keyWords":2},{"key":"mod","endIndex":4482,"keyWords":10},{"key":"moh","endIndex":4483,"keyWords":1},{"key":"moi","endIndex":4485,"keyWords":2},{"key":"mol","endIndex":4491,"keyWords":6},{"key":"mom","endIndex":4494,"keyWords":3},{"key":"mon","endIndex":4517,"keyWords":23},{"key":"moo","endIndex":4524,"keyWords":7},{"key":"mop","endIndex":4525,"keyWords":1},{"key":"mor","endIndex":4541,"keyWords":16},{"key":"mos","endIndex":4547,"keyWords":6},{"key":"mot","endIndex":4560,"keyWords":13},{"key":"mou","endIndex":4572,"keyWords":12},{"key":"mov","endIndex":4577,"keyWords":5},{"key":"mow","endIndex":4578,"keyWords":1},{"key":"muc","endIndex":4580,"keyWords":2},{"key":"mud","endIndex":4582,"keyWords":2},{"key":"mue","endIndex":4583,"keyWords":1},{"key":"muf","endIndex":4584,"keyWords":1},{"key":"mug","endIndex":4586,"keyWords":2},{"key":"mul","endIndex":4589,"keyWords":3},{"key":"mum","endIndex":4592,"keyWords":3},{"key":"mun","endIndex":4594,"keyWords":2},{"key":"mur","endIndex":4598,"keyWords":4},{"key":"mus","endIndex":4614,"keyWords":16},{"key":"mut","endIndex":4620,"keyWords":6},{"key":"muz","endIndex":4621,"keyWords":1},{"key":"myr","endIndex":4622,"keyWords":1},{"key":"mys","endIndex":4625,"keyWords":3},{"key":"myt","endIndex":4628,"keyWords":3},{"key":"nad","endIndex":4629,"keyWords":1},{"key":"nai","endIndex":4631,"keyWords":2},{"key":"nak","endIndex":4632,"keyWords":1},{"key":"nam","endIndex":4635,"keyWords":3},{"key":"nan","endIndex":4636,"keyWords":1},{"key":"nap","endIndex":4640,"keyWords":4},{"key":"nar","endIndex":4645,"keyWords":5},{"key":"nas","endIndex":4646,"keyWords":1},{"key":"nat","endIndex":4653,"keyWords":7},{"key":"nau","endIndex":4656,"keyWords":3},{"key":"nav","endIndex":4660,"keyWords":4},{"key":"nea","endIndex":4664,"keyWords":4},{"key":"neb","endIndex":4665,"keyWords":1},{"key":"nec","endIndex":4671,"keyWords":6},{"key":"nee","endIndex":4674,"keyWords":3},{"key":"neg","endIndex":4680,"keyWords":6},{"key":"nei","endIndex":4683,"keyWords":3},{"key":"neo","endIndex":4684,"keyWords":1},{"key":"nep","endIndex":4687,"keyWords":3},{"key":"ner","endIndex":4689,"keyWords":2},{"key":"nes","endIndex":4690,"keyWords":1},{"key":"net","endIndex":4692,"keyWords":2},{"key":"neu","endIndex":4697,"keyWords":5},{"key":"nev","endIndex":4699,"keyWords":2},{"key":"new","endIndex":4705,"keyWords":6},{"key":"nib","endIndex":4706,"keyWords":1},{"key":"nic","endIndex":4712,"keyWords":6},{"key":"nie","endIndex":4713,"keyWords":1},{"key":"nig","endIndex":4721,"keyWords":8},{"key":"nin","endIndex":4726,"keyWords":5},{"key":"nip","endIndex":4727,"keyWords":1},{"key":"nit","endIndex":4728,"keyWords":1},{"key":"nob","endIndex":4731,"keyWords":3},{"key":"noc","endIndex":4732,"keyWords":1},{"key":"nod","endIndex":4733,"keyWords":1},{"key":"noi","endIndex":4735,"keyWords":2},{"key":"nom","endIndex":4737,"keyWords":2},{"key":"non","endIndex":4740,"keyWords":3},{"key":"noo","endIndex":4743,"keyWords":3},{"key":"nor","endIndex":4753,"keyWords":10},{"key":"nos","endIndex":4760,"keyWords":7},{"key":"not","endIndex":4770,"keyWords":10},{"key":"nou","endIndex":4771,"keyWords":1},{"key":"nov","endIndex":4775,"keyWords":4},{"key":"now","endIndex":4777,"keyWords":2},{"key":"nox","endIndex":4778,"keyWords":1},{"key":"noz","endIndex":4779,"keyWords":1},{"key":"nua","endIndex":4780,"keyWords":1},{"key":"nuc","endIndex":4782,"keyWords":2},{"key":"nud","endIndex":4784,"keyWords":2},{"key":"nug","endIndex":4785,"keyWords":1},{"key":"nui","endIndex":4786,"keyWords":1},{"key":"nul","endIndex":4787,"keyWords":1},{"key":"num","endIndex":4792,"keyWords":5},{"key":"nur","endIndex":4796,"keyWords":4},{"key":"nut","endIndex":4800,"keyWords":4},{"key":"nyl","endIndex":4801,"keyWords":1},{"key":"oas","endIndex":4802,"keyWords":1},{"key":"oat","endIndex":4804,"keyWords":2},{"key":"obe","endIndex":4807,"keyWords":3},{"key":"obi","endIndex":4808,"keyWords":1},{"key":"obj","endIndex":4811,"keyWords":3},{"key":"obl","endIndex":4814,"keyWords":3},{"key":"obn","endIndex":4815,"keyWords":1},{"key":"obo","endIndex":4816,"keyWords":1},{"key":"obs","endIndex":4827,"keyWords":11},{"key":"obt","endIndex":4829,"keyWords":2},{"key":"obv","endIndex":4831,"keyWords":2},{"key":"occ","endIndex":4835,"keyWords":4},{"key":"oce","endIndex":4836,"keyWords":1},{"key":"oct","endIndex":4840,"keyWords":4},{"key":"odo","endIndex":4841,"keyWords":1},{"key":"off","endIndex":4851,"keyWords":10},{"key":"oft","endIndex":4852,"keyWords":1},{"key":"ogl","endIndex":4853,"keyWords":1},{"key":"ogr","endIndex":4854,"keyWords":1},{"key":"ohi","endIndex":4855,"keyWords":1},{"key":"ohm","endIndex":4856,"keyWords":1},{"key":"oin","endIndex":4857,"keyWords":1},{"key":"okl","endIndex":4858,"keyWords":1},{"key":"oli","endIndex":4859,"keyWords":1},{"key":"oly","endIndex":4860,"keyWords":1},{"key":"ome","endIndex":4861,"keyWords":1},{"key":"omi","endIndex":4864,"keyWords":3},{"key":"omn","endIndex":4865,"keyWords":1},{"key":"onc","endIndex":4866,"keyWords":1},{"key":"one","endIndex":4868,"keyWords":2},{"key":"oni","endIndex":4869,"keyWords":1},{"key":"onl","endIndex":4871,"keyWords":2},{"key":"onu","endIndex":4872,"keyWords":1},{"key":"onw","endIndex":4873,"keyWords":1},{"key":"oop","endIndex":4874,"keyWords":1},{"key":"ooz","endIndex":4875,"keyWords":1},{"key":"opa","endIndex":4877,"keyWords":2},{"key":"ope","endIndex":4886,"keyWords":9},{"key":"opi","endIndex":4888,"keyWords":2},{"key":"opp","endIndex":4893,"keyWords":5},{"key":"opt","endIndex":4897,"keyWords":4},{"key":"ora","endIndex":4901,"keyWords":4},{"key":"orb","endIndex":4902,"keyWords":1},{"key":"orc","endIndex":4905,"keyWords":3},{"key":"ord","endIndex":4908,"keyWords":3},{"key":"ore","endIndex":4909,"keyWords":1},{"key":"org","endIndex":4915,"keyWords":6},{"key":"ori","endIndex":4918,"keyWords":3},{"key":"orn","endIndex":4919,"keyWords":1},{"key":"orp","endIndex":4921,"keyWords":2},{"key":"ort","endIndex":4923,"keyWords":2},{"key":"osc","endIndex":4924,"keyWords":1},{"key":"ost","endIndex":4925,"keyWords":1},{"key":"oth","endIndex":4927,"keyWords":2},{"key":"ott","endIndex":4928,"keyWords":1},{"key":"ouc","endIndex":4929,"keyWords":1},{"key":"oun","endIndex":4930,"keyWords":1},{"key":"our","endIndex":4932,"keyWords":2},{"key":"ous","endIndex":4933,"keyWords":1},{"key":"out","endIndex":4953,"keyWords":20},{"key":"ova","endIndex":4956,"keyWords":3},{"key":"ove","endIndex":4984,"keyWords":28},{"key":"own","endIndex":4986,"keyWords":2},{"key":"oxf","endIndex":4987,"keyWords":1},{"key":"oxi","endIndex":4988,"keyWords":1},{"key":"oxy","endIndex":4989,"keyWords":1},{"key":"oys","endIndex":4990,"keyWords":1},{"key":"pac","endIndex":4999,"keyWords":9},{"key":"pad","endIndex":5002,"keyWords":3},{"key":"pag","endIndex":5006,"keyWords":4},{"key":"pai","endIndex":5013,"keyWords":7},{"key":"paj","endIndex":5014,"keyWords":1},{"key":"pak","endIndex":5016,"keyWords":2},{"key":"pal","endIndex":5023,"keyWords":7},{"key":"pam","endIndex":5025,"keyWords":2},{"key":"pan","endIndex":5040,"keyWords":15},{"key":"pap","endIndex":5045,"keyWords":5},{"key":"par","endIndex":5088,"keyWords":43},{"key":"pas","endIndex":5105,"keyWords":17},{"key":"pat","endIndex":5120,"keyWords":15},{"key":"pau","endIndex":5122,"keyWords":2},{"key":"pav","endIndex":5124,"keyWords":2},{"key":"paw","endIndex":5126,"keyWords":2},{"key":"pay","endIndex":5128,"keyWords":2},{"key":"pea","endIndex":5141,"keyWords":13},{"key":"peb","endIndex":5142,"keyWords":1},{"key":"pec","endIndex":5145,"keyWords":3},{"key":"ped","endIndex":5152,"keyWords":7},{"key":"pee","endIndex":5156,"keyWords":4},{"key":"pek","endIndex":5157,"keyWords":1},{"key":"pel","endIndex":5160,"keyWords":3},{"key":"pen","endIndex":5179,"keyWords":19},{"key":"peo","endIndex":5180,"keyWords":1},{"key":"per","endIndex":5216,"keyWords":36},{"key":"pes","endIndex":5220,"keyWords":4},{"key":"pet","endIndex":5227,"keyWords":7},{"key":"pew","endIndex":5228,"keyWords":1},{"key":"pha","endIndex":5231,"keyWords":3},{"key":"phe","endIndex":5233,"keyWords":2},{"key":"phi","endIndex":5235,"keyWords":2},{"key":"phl","endIndex":5236,"keyWords":1},{"key":"pho","endIndex":5243,"keyWords":7},{"key":"phr","endIndex":5245,"keyWords":2},{"key":"phy","endIndex":5248,"keyWords":3},{"key":"pia","endIndex":5250,"keyWords":2},{"key":"pic","endIndex":5257,"keyWords":7},{"key":"pid","endIndex":5258,"keyWords":1},{"key":"pie","endIndex":5263,"keyWords":5},{"key":"pig","endIndex":5269,"keyWords":6},{"key":"pik","endIndex":5270,"keyWords":1},{"key":"pil","endIndex":5277,"keyWords":7},{"key":"pim","endIndex":5279,"keyWords":2},{"key":"pin","endIndex":5287,"keyWords":8},{"key":"pio","endIndex":5289,"keyWords":2},{"key":"pip","endIndex":5291,"keyWords":2},{"key":"piq","endIndex":5292,"keyWords":1},{"key":"pir","endIndex":5295,"keyWords":3},{"key":"pis","endIndex":5299,"keyWords":4},{"key":"pit","endIndex":5305,"keyWords":6},{"key":"piv","endIndex":5306,"keyWords":1},{"key":"pix","endIndex":5308,"keyWords":2},{"key":"pla","endIndex":5340,"keyWords":32},{"key":"ple","endIndex":5352,"keyWords":12},{"key":"pli","endIndex":5355,"keyWords":3},{"key":"plo","endIndex":5358,"keyWords":3},{"key":"plu","endIndex":5369,"keyWords":11},{"key":"ply","endIndex":5370,"keyWords":1},{"key":"pne","endIndex":5371,"keyWords":1},{"key":"poa","endIndex":5373,"keyWords":2},{"key":"poc","endIndex":5375,"keyWords":2},{"key":"poe","endIndex":5378,"keyWords":3},{"key":"poi","endIndex":5381,"keyWords":3},{"key":"pok","endIndex":5382,"keyWords":1},{"key":"pol","endIndex":5401,"keyWords":19},{"key":"pon","endIndex":5406,"keyWords":5},{"key":"poo","endIndex":5408,"keyWords":2},{"key":"pop","endIndex":5415,"keyWords":7},{"key":"por","endIndex":5432,"keyWords":17},{"key":"pos","endIndex":5446,"keyWords":14},{"key":"pot","endIndex":5451,"keyWords":5},{"key":"pou","endIndex":5456,"keyWords":5},{"key":"pov","endIndex":5457,"keyWords":1},{"key":"pow","endIndex":5462,"keyWords":5},{"key":"pra","endIndex":5473,"keyWords":11},{"key":"pre","endIndex":5512,"keyWords":39},{"key":"pri","endIndex":5545,"keyWords":33},{"key":"pro","endIndex":5613,"keyWords":68},{"key":"pru","endIndex":5617,"keyWords":4},{"key":"psa","endIndex":5618,"keyWords":1},{"key":"pse","endIndex":5619,"keyWords":1},{"key":"psy","endIndex":5623,"keyWords":4},{"key":"pub","endIndex":5629,"keyWords":6},{"key":"puc","endIndex":5630,"keyWords":1},{"key":"pud","endIndex":5632,"keyWords":2},{"key":"pue","endIndex":5633,"keyWords":1},{"key":"puf","endIndex":5635,"keyWords":2},{"key":"pul","endIndex":5641,"keyWords":6},{"key":"pum","endIndex":5644,"keyWords":3},{"key":"pun","endIndex":5651,"keyWords":7},{"key":"pup","endIndex":5654,"keyWords":3},{"key":"pur","endIndex":5668,"keyWords":14},{"key":"pus","endIndex":5670,"keyWords":2},{"key":"put","endIndex":5672,"keyWords":2},{"key":"puz","endIndex":5673,"keyWords":1},{"key":"pyg","endIndex":5674,"keyWords":1},{"key":"pyl","endIndex":5675,"keyWords":1},{"key":"pyr","endIndex":5677,"keyWords":2},{"key":"pyt","endIndex":5678,"keyWords":1},{"key":"qua","endIndex":5695,"keyWords":17},{"key":"que","endIndex":5702,"keyWords":7},{"key":"qui","endIndex":5715,"keyWords":13},{"key":"quo","endIndex":5719,"keyWords":4},{"key":"rab","endIndex":5723,"keyWords":4},{"key":"rac","endIndex":5731,"keyWords":8},{"key":"rad","endIndex":5740,"keyWords":9},{"key":"raf","endIndex":5743,"keyWords":3},{"key":"rag","endIndex":5744,"keyWords":1},{"key":"rai","endIndex":5758,"keyWords":14},{"key":"raj","endIndex":5759,"keyWords":1},{"key":"rak","endIndex":5760,"keyWords":1},{"key":"ral","endIndex":5761,"keyWords":1},{"key":"ram","endIndex":5765,"keyWords":4},{"key":"ran","endIndex":5770,"keyWords":5},{"key":"rap","endIndex":5776,"keyWords":6},{"key":"rar","endIndex":5778,"keyWords":2},{"key":"ras","endIndex":5782,"keyWords":4},{"key":"rat","endIndex":5789,"keyWords":7},{"key":"rav","endIndex":5792,"keyWords":3},{"key":"ray","endIndex":5793,"keyWords":1},{"key":"raz","endIndex":5794,"keyWords":1},{"key":"rea","endIndex":5809,"keyWords":15},{"key":"reb","endIndex":5815,"keyWords":6},{"key":"rec","endIndex":5845,"keyWords":30},{"key":"red","endIndex":5851,"keyWords":6},{"key":"ree","endIndex":5856,"keyWords":5},{"key":"ref","endIndex":5876,"keyWords":20},{"key":"reg","endIndex":5890,"keyWords":14},{"key":"reh","endIndex":5891,"keyWords":1},{"key":"rei","endIndex":5895,"keyWords":4},{"key":"rej","endIndex":5897,"keyWords":2},{"key":"rel","endIndex":5914,"keyWords":17},{"key":"rem","endIndex":5926,"keyWords":12},{"key":"ren","endIndex":5934,"keyWords":8},{"key":"rep","endIndex":5949,"keyWords":15},{"key":"req","endIndex":5951,"keyWords":2},{"key":"res","endIndex":5977,"keyWords":26},{"key":"ret","endIndex":5988,"keyWords":11},{"key":"reu","endIndex":5989,"keyWords":1},{"key":"rev","endIndex":6007,"keyWords":18},{"key":"rew","endIndex":6010,"keyWords":3},{"key":"rhe","endIndex":6011,"keyWords":1},{"key":"rhi","endIndex":6012,"keyWords":1},{"key":"rho","endIndex":6013,"keyWords":1},{"key":"rhu","endIndex":6014,"keyWords":1},{"key":"rhy","endIndex":6016,"keyWords":2},{"key":"rib","endIndex":6017,"keyWords":1},{"key":"ric","endIndex":6021,"keyWords":4},{"key":"rid","endIndex":6026,"keyWords":5},{"key":"rif","endIndex":6028,"keyWords":2},{"key":"rig","endIndex":6031,"keyWords":3},{"key":"rin","endIndex":6032,"keyWords":1},{"key":"rio","endIndex":6033,"keyWords":1},{"key":"rip","endIndex":6037,"keyWords":4},{"key":"ris","endIndex":6039,"keyWords":2},{"key":"rit","endIndex":6041,"keyWords":2},{"key":"riv","endIndex":6046,"keyWords":5},{"key":"roa","endIndex":6051,"keyWords":5},{"key":"rob","endIndex":6056,"keyWords":5},{"key":"roc","endIndex":6059,"keyWords":3},{"key":"rod","endIndex":6060,"keyWords":1},{"key":"rog","endIndex":6061,"keyWords":1},{"key":"rol","endIndex":6065,"keyWords":4},{"key":"rom","endIndex":6070,"keyWords":5},{"key":"roo","endIndex":6078,"keyWords":8},{"key":"rop","endIndex":6079,"keyWords":1},{"key":"ros","endIndex":6083,"keyWords":4},{"key":"rot","endIndex":6086,"keyWords":3},{"key":"rou","endIndex":6090,"keyWords":4},{"key":"rov","endIndex":6091,"keyWords":1},{"key":"row","endIndex":6094,"keyWords":3},{"key":"roy","endIndex":6096,"keyWords":2},{"key":"rub","endIndex":6100,"keyWords":4},{"key":"ruc","endIndex":6101,"keyWords":1},{"key":"rud","endIndex":6104,"keyWords":3},{"key":"ruf","endIndex":6106,"keyWords":2},{"key":"rug","endIndex":6107,"keyWords":1},{"key":"rui","endIndex":6108,"keyWords":1},{"key":"rul","endIndex":6111,"keyWords":3},{"key":"rum","endIndex":6117,"keyWords":6},{"key":"run","endIndex":6121,"keyWords":4},{"key":"rup","endIndex":6123,"keyWords":2},{"key":"rur","endIndex":6124,"keyWords":1},{"key":"rus","endIndex":6129,"keyWords":5},{"key":"rut","endIndex":6130,"keyWords":1},{"key":"sab","endIndex":6133,"keyWords":3},{"key":"sac","endIndex":6139,"keyWords":6},{"key":"sad","endIndex":6142,"keyWords":3},{"key":"saf","endIndex":6145,"keyWords":3},{"key":"sag","endIndex":6147,"keyWords":2},{"key":"sah","endIndex":6148,"keyWords":1},{"key":"sai","endIndex":6152,"keyWords":4},{"key":"sak","endIndex":6153,"keyWords":1},{"key":"sal","endIndex":6164,"keyWords":11},{"key":"sam","endIndex":6166,"keyWords":2},{"key":"san","endIndex":6177,"keyWords":11},{"key":"sap","endIndex":6179,"keyWords":2},{"key":"sar","endIndex":6181,"keyWords":2},{"key":"sat","endIndex":6190,"keyWords":9},{"key":"sau","endIndex":6195,"keyWords":5},{"key":"sav","endIndex":6199,"keyWords":4},{"key":"saw","endIndex":6200,"keyWords":1},{"key":"sax","endIndex":6203,"keyWords":3},{"key":"say","endIndex":6204,"keyWords":1},{"key":"sca","endIndex":6222,"keyWords":18},{"key":"sce","endIndex":6227,"keyWords":5},{"key":"sch","endIndex":6234,"keyWords":7},{"key":"sci","endIndex":6237,"keyWords":3},{"key":"sco","endIndex":6254,"keyWords":17},{"key":"scr","endIndex":6269,"keyWords":15},{"key":"scu","endIndex":6273,"keyWords":4},{"key":"scy","endIndex":6274,"keyWords":1},{"key":"sea","endIndex":6286,"keyWords":12},{"key":"sec","endIndex":6298,"keyWords":12},{"key":"sed","endIndex":6302,"keyWords":4},{"key":"see","endIndex":6311,"keyWords":9},{"key":"seg","endIndex":6312,"keyWords":1},{"key":"sei","endIndex":6314,"keyWords":2},{"key":"sel","endIndex":6323,"keyWords":9},{"key":"sem","endIndex":6330,"keyWords":7},{"key":"sen","endIndex":6342,"keyWords":12},{"key":"sep","endIndex":6346,"keyWords":4},{"key":"seq","endIndex":6348,"keyWords":2},{"key":"ser","endIndex":6366,"keyWords":18},{"key":"ses","endIndex":6367,"keyWords":1},{"key":"set","endIndex":6370,"keyWords":3},{"key":"sev","endIndex":6378,"keyWords":8},{"key":"sew","endIndex":6381,"keyWords":3},{"key":"sex","endIndex":6384,"keyWords":3},{"key":"sha","endIndex":6408,"keyWords":24},{"key":"she","endIndex":6424,"keyWords":16},{"key":"shi","endIndex":6436,"keyWords":12},{"key":"sho","endIndex":6464,"keyWords":28},{"key":"shr","endIndex":6474,"keyWords":10},{"key":"shu","endIndex":6480,"keyWords":6},{"key":"sib","endIndex":6481,"keyWords":1},{"key":"sic","endIndex":6485,"keyWords":4},{"key":"sid","endIndex":6488,"keyWords":3},{"key":"sie","endIndex":6491,"keyWords":3},{"key":"sig","endIndex":6496,"keyWords":5},{"key":"sil","endIndex":6507,"keyWords":11},{"key":"sim","endIndex":6513,"keyWords":6},{"key":"sin","endIndex":6529,"keyWords":16},{"key":"sip","endIndex":6530,"keyWords":1},{"key":"sir","endIndex":6531,"keyWords":1},{"key":"sis","endIndex":6533,"keyWords":2},{"key":"sit","endIndex":6536,"keyWords":3},{"key":"six","endIndex":6540,"keyWords":4},{"key":"siz","endIndex":6542,"keyWords":2},{"key":"ska","endIndex":6545,"keyWords":3},{"key":"ske","endIndex":6548,"keyWords":3},{"key":"ski","endIndex":6560,"keyWords":12},{"key":"sku","endIndex":6562,"keyWords":2},{"key":"sky","endIndex":6563,"keyWords":1},{"key":"sla","endIndex":6578,"keyWords":15},{"key":"sle","endIndex":6586,"keyWords":8},{"key":"sli","endIndex":6597,"keyWords":11},{"key":"slo","endIndex":6605,"keyWords":8},{"key":"slu","endIndex":6613,"keyWords":8},{"key":"sma","endIndex":6617,"keyWords":4},{"key":"sme","endIndex":6620,"keyWords":3},{"key":"smi","endIndex":6622,"keyWords":2},{"key":"smo","endIndex":6628,"keyWords":6},{"key":"smu","endIndex":6630,"keyWords":2},{"key":"sna","endIndex":6637,"keyWords":7},{"key":"sne","endIndex":6641,"keyWords":4},{"key":"sni","endIndex":6643,"keyWords":2},{"key":"sno","endIndex":6655,"keyWords":12},{"key":"snu","endIndex":6656,"keyWords":1},{"key":"soa","endIndex":6659,"keyWords":3},{"key":"sob","endIndex":6660,"keyWords":1},{"key":"soc","endIndex":6670,"keyWords":10},{"key":"sod","endIndex":6671,"keyWords":1},{"key":"sof","endIndex":6675,"keyWords":4},{"key":"soi","endIndex":6676,"keyWords":1},{"key":"sol","endIndex":6691,"keyWords":15},{"key":"som","endIndex":6701,"keyWords":10},{"key":"son","endIndex":6703,"keyWords":2},{"key":"soo","endIndex":6705,"keyWords":2},{"key":"sop","endIndex":6707,"keyWords":2},{"key":"sor","endIndex":6710,"keyWords":3},{"key":"sos","endIndex":6711,"keyWords":1},{"key":"sou","endIndex":6722,"keyWords":11},{"key":"sov","endIndex":6724,"keyWords":2},{"key":"spa","endIndex":6742,"keyWords":18},{"key":"spe","endIndex":6763,"keyWords":21},{"key":"sph","endIndex":6765,"keyWords":2},{"key":"spi","endIndex":6782,"keyWords":17},{"key":"spl","endIndex":6788,"keyWords":6},{"key":"spo","endIndex":6803,"keyWords":15},{"key":"spr","endIndex":6814,"keyWords":11},{"key":"spu","endIndex":6817,"keyWords":3},{"key":"squ","endIndex":6829,"keyWords":12},{"key":"sta","endIndex":6878,"keyWords":49},{"key":"ste","endIndex":6901,"keyWords":23},{"key":"sti","endIndex":6918,"keyWords":17},{"key":"sto","endIndex":6936,"keyWords":18},{"key":"str","endIndex":6971,"keyWords":35},{"key":"stu","endIndex":6985,"keyWords":14},{"key":"sty","endIndex":6987,"keyWords":2},{"key":"sub","endIndex":7004,"keyWords":17},{"key":"suc","endIndex":7013,"keyWords":9},{"key":"sud","endIndex":7017,"keyWords":4},{"key":"sue","endIndex":7019,"keyWords":2},{"key":"suf","endIndex":7024,"keyWords":5},{"key":"sug","endIndex":7026,"keyWords":2},{"key":"sui","endIndex":7030,"keyWords":4},{"key":"sul","endIndex":7037,"keyWords":7},{"key":"sum","endIndex":7043,"keyWords":6},{"key":"sun","endIndex":7057,"keyWords":14},{"key":"sup","endIndex":7067,"keyWords":10},{"key":"sur","endIndex":7091,"keyWords":24},{"key":"sus","endIndex":7095,"keyWords":4},{"key":"swa","endIndex":7102,"keyWords":7},{"key":"swe","endIndex":7111,"keyWords":9},{"key":"swi","endIndex":7123,"keyWords":12},{"key":"swo","endIndex":7128,"keyWords":5},{"key":"syc","endIndex":7130,"keyWords":2},{"key":"syl","endIndex":7132,"keyWords":2},{"key":"sym","endIndex":7139,"keyWords":7},{"key":"syn","endIndex":7148,"keyWords":9},{"key":"syp","endIndex":7149,"keyWords":1},{"key":"syr","endIndex":7153,"keyWords":4},{"key":"sys","endIndex":7154,"keyWords":1},{"key":"tab","endIndex":7158,"keyWords":4},{"key":"tac","endIndex":7161,"keyWords":3},{"key":"tad","endIndex":7162,"keyWords":1},{"key":"tai","endIndex":7166,"keyWords":4},{"key":"tak","endIndex":7169,"keyWords":3},{"key":"tal","endIndex":7178,"keyWords":9},{"key":"tam","endIndex":7181,"keyWords":3},{"key":"tan","endIndex":7192,"keyWords":11},{"key":"tap","endIndex":7194,"keyWords":2},{"key":"tar","endIndex":7200,"keyWords":6},{"key":"tas","endIndex":7204,"keyWords":4},{"key":"tat","endIndex":7205,"keyWords":1},{"key":"tau","endIndex":7208,"keyWords":3},{"key":"taw","endIndex":7209,"keyWords":1},{"key":"tax","endIndex":7212,"keyWords":3},{"key":"tea","endIndex":7225,"keyWords":13},{"key":"tec","endIndex":7227,"keyWords":2},{"key":"ted","endIndex":7229,"keyWords":2},{"key":"tee","endIndex":7231,"keyWords":2},{"key":"tel","endIndex":7241,"keyWords":10},{"key":"tem","endIndex":7250,"keyWords":9},{"key":"ten","endIndex":7265,"keyWords":15},{"key":"tep","endIndex":7266,"keyWords":1},{"key":"ter","endIndex":7278,"keyWords":12},{"key":"tes","endIndex":7283,"keyWords":5},{"key":"tet","endIndex":7284,"keyWords":1},{"key":"tex","endIndex":7288,"keyWords":4},{"key":"tha","endIndex":7294,"keyWords":6},{"key":"the","endIndex":7312,"keyWords":18},{"key":"thi","endIndex":7331,"keyWords":19},{"key":"tho","endIndex":7336,"keyWords":5},{"key":"thr","endIndex":7353,"keyWords":17},{"key":"thu","endIndex":7359,"keyWords":6},{"key":"thw","endIndex":7360,"keyWords":1},{"key":"thy","endIndex":7361,"keyWords":1},{"key":"tia","endIndex":7362,"keyWords":1},{"key":"tic","endIndex":7366,"keyWords":4},{"key":"tid","endIndex":7369,"keyWords":3},{"key":"tie","endIndex":7370,"keyWords":1},{"key":"tig","endIndex":7373,"keyWords":3},{"key":"til","endIndex":7375,"keyWords":2},{"key":"tim","endIndex":7382,"keyWords":7},{"key":"tin","endIndex":7386,"keyWords":4},{"key":"tip","endIndex":7388,"keyWords":2},{"key":"tir","endIndex":7392,"keyWords":4},{"key":"tis","endIndex":7393,"keyWords":1},{"key":"tit","endIndex":7395,"keyWords":2},{"key":"toa","endIndex":7398,"keyWords":3},{"key":"tob","endIndex":7399,"keyWords":1},{"key":"tod","endIndex":7401,"keyWords":2},{"key":"toe","endIndex":7402,"keyWords":1},{"key":"tof","endIndex":7403,"keyWords":1},{"key":"tog","endIndex":7404,"keyWords":1},{"key":"toi","endIndex":7405,"keyWords":1},{"key":"tok","endIndex":7407,"keyWords":2},{"key":"tol","endIndex":7410,"keyWords":3},{"key":"tom","endIndex":7415,"keyWords":5},{"key":"ton","endIndex":7422,"keyWords":7},{"key":"too","endIndex":7427,"keyWords":5},{"key":"top","endIndex":7428,"keyWords":1},{"key":"tor","endIndex":7437,"keyWords":9},{"key":"tos","endIndex":7438,"keyWords":1},{"key":"tot","endIndex":7439,"keyWords":1},{"key":"tou","endIndex":7445,"keyWords":6},{"key":"tow","endIndex":7448,"keyWords":3},{"key":"tox","endIndex":7449,"keyWords":1},{"key":"tra","endIndex":7488,"keyWords":39},{"key":"tre","endIndex":7508,"keyWords":20},{"key":"tri","endIndex":7529,"keyWords":21},{"key":"tro","endIndex":7542,"keyWords":13},{"key":"tru","endIndex":7556,"keyWords":14},{"key":"tub","endIndex":7559,"keyWords":3},{"key":"tuc","endIndex":7560,"keyWords":1},{"key":"tue","endIndex":7561,"keyWords":1},{"key":"tui","endIndex":7562,"keyWords":1},{"key":"tul","endIndex":7563,"keyWords":1},{"key":"tum","endIndex":7566,"keyWords":3},{"key":"tun","endIndex":7570,"keyWords":4},{"key":"tur","endIndex":7582,"keyWords":12},{"key":"tus","endIndex":7583,"keyWords":1},{"key":"tut","endIndex":7585,"keyWords":2},{"key":"tux","endIndex":7586,"keyWords":1},{"key":"twe","endIndex":7592,"keyWords":6},{"key":"twi","endIndex":7599,"keyWords":7},{"key":"tyc","endIndex":7600,"keyWords":1},{"key":"typ","endIndex":7606,"keyWords":6},{"key":"tyr","endIndex":7609,"keyWords":3},{"key":"udd","endIndex":7610,"keyWords":1},{"key":"uga","endIndex":7611,"keyWords":1},{"key":"ugl","endIndex":7612,"keyWords":1},{"key":"ukr","endIndex":7613,"keyWords":1},{"key":"ulc","endIndex":7614,"keyWords":1},{"key":"ult","endIndex":7617,"keyWords":3},{"key":"umb","endIndex":7619,"keyWords":2},{"key":"ump","endIndex":7620,"keyWords":1},{"key":"una","endIndex":7621,"keyWords":1},{"key":"unb","endIndex":7622,"keyWords":1},{"key":"unc","endIndex":7626,"keyWords":4},{"key":"und","endIndex":7638,"keyWords":12},{"key":"unf","endIndex":7643,"keyWords":5},{"key":"ung","endIndex":7644,"keyWords":1},{"key":"unh","endIndex":7645,"keyWords":1},{"key":"uni","endIndex":7657,"keyWords":12},{"key":"unj","endIndex":7658,"keyWords":1},{"key":"unk","endIndex":7659,"keyWords":1},{"key":"unl","endIndex":7664,"keyWords":5},{"key":"unn","endIndex":7665,"keyWords":1},{"key":"unp","endIndex":7668,"keyWords":3},{"key":"unr","endIndex":7672,"keyWords":4},{"key":"uns","endIndex":7675,"keyWords":3},{"key":"unt","endIndex":7677,"keyWords":2},{"key":"unu","endIndex":7678,"keyWords":1},{"key":"unw","endIndex":7680,"keyWords":2},{"key":"upd","endIndex":7681,"keyWords":1},{"key":"uph","endIndex":7683,"keyWords":2},{"key":"upl","endIndex":7684,"keyWords":1},{"key":"upp","endIndex":7685,"keyWords":1},{"key":"upr","endIndex":7687,"keyWords":2},{"key":"ups","endIndex":7690,"keyWords":3},{"key":"ura","endIndex":7691,"keyWords":1},{"key":"urb","endIndex":7692,"keyWords":1},{"key":"urc","endIndex":7693,"keyWords":1},{"key":"urg","endIndex":7695,"keyWords":2},{"key":"uri","endIndex":7698,"keyWords":3},{"key":"uru","endIndex":7699,"keyWords":1},{"key":"usa","endIndex":7700,"keyWords":1},{"key":"use","endIndex":7703,"keyWords":3},{"key":"ush","endIndex":7704,"keyWords":1},{"key":"uss","endIndex":7705,"keyWords":1},{"key":"usu","endIndex":7710,"keyWords":5},{"key":"uta","endIndex":7711,"keyWords":1},{"key":"uti","endIndex":7712,"keyWords":1},{"key":"utm","endIndex":7713,"keyWords":1},{"key":"uto","endIndex":7714,"keyWords":1},{"key":"utt","endIndex":7715,"keyWords":1},{"key":"vac","endIndex":7721,"keyWords":6},{"key":"vag","endIndex":7725,"keyWords":4},{"key":"val","endIndex":7732,"keyWords":7},{"key":"vam","endIndex":7733,"keyWords":1},{"key":"van","endIndex":7740,"keyWords":7},{"key":"vap","endIndex":7741,"keyWords":1},{"key":"var","endIndex":7749,"keyWords":8},{"key":"vas","endIndex":7751,"keyWords":2},{"key":"vau","endIndex":7752,"keyWords":1},{"key":"vea","endIndex":7753,"keyWords":1},{"key":"veg","endIndex":7754,"keyWords":1},{"key":"veh","endIndex":7756,"keyWords":2},{"key":"vei","endIndex":7758,"keyWords":2},{"key":"vel","endIndex":7760,"keyWords":2},{"key":"ven","endIndex":7770,"keyWords":10},{"key":"ver","endIndex":7788,"keyWords":18},{"key":"ves","endIndex":7791,"keyWords":3},{"key":"vet","endIndex":7793,"keyWords":2},{"key":"via","endIndex":7795,"keyWords":2},{"key":"vib","endIndex":7797,"keyWords":2},{"key":"vic","endIndex":7805,"keyWords":8},{"key":"vid","endIndex":7806,"keyWords":1},{"key":"vie","endIndex":7810,"keyWords":4},{"key":"vig","endIndex":7812,"keyWords":2},{"key":"vil","endIndex":7817,"keyWords":5},{"key":"vin","endIndex":7820,"keyWords":3},{"key":"vio","endIndex":7827,"keyWords":7},{"key":"vip","endIndex":7828,"keyWords":1},{"key":"vir","endIndex":7836,"keyWords":8},{"key":"vis","endIndex":7842,"keyWords":6},{"key":"vit","endIndex":7844,"keyWords":2},{"key":"viv","endIndex":7845,"keyWords":1},{"key":"voc","endIndex":7847,"keyWords":2},{"key":"vod","endIndex":7848,"keyWords":1},{"key":"vog","endIndex":7849,"keyWords":1},{"key":"voi","endIndex":7850,"keyWords":1},{"key":"vol","endIndex":7861,"keyWords":11},{"key":"vom","endIndex":7862,"keyWords":1},{"key":"vor","endIndex":7864,"keyWords":2},{"key":"vot","endIndex":7866,"keyWords":2},{"key":"vou","endIndex":7867,"keyWords":1},{"key":"vow","endIndex":7868,"keyWords":1},{"key":"voy","endIndex":7869,"keyWords":1},{"key":"vul","endIndex":7871,"keyWords":2},{"key":"wad","endIndex":7872,"keyWords":1},{"key":"waf","endIndex":7874,"keyWords":2},{"key":"wag","endIndex":7877,"keyWords":3},{"key":"wai","endIndex":7885,"keyWords":8},{"key":"wak","endIndex":7886,"keyWords":1},{"key":"wal","endIndex":7898,"keyWords":12},{"key":"wan","endIndex":7903,"keyWords":5},{"key":"war","endIndex":7924,"keyWords":21},{"key":"was","endIndex":7933,"keyWords":9},{"key":"wat","endIndex":7943,"keyWords":10},{"key":"wav","endIndex":7946,"keyWords":3},{"key":"wax","endIndex":7947,"keyWords":1},{"key":"way","endIndex":7948,"keyWords":1},{"key":"wea","endIndex":7962,"keyWords":14},{"key":"wed","endIndex":7965,"keyWords":3},{"key":"wee","endIndex":7971,"keyWords":6},{"key":"wei","endIndex":7975,"keyWords":4},{"key":"wel","endIndex":7983,"keyWords":8},{"key":"wer","endIndex":7984,"keyWords":1},{"key":"wes","endIndex":7987,"keyWords":3},{"key":"wha","endIndex":7992,"keyWords":5},{"key":"whe","endIndex":7998,"keyWords":6},{"key":"whi","endIndex":8012,"keyWords":14},{"key":"who","endIndex":8017,"keyWords":5},{"key":"wic","endIndex":8020,"keyWords":3},{"key":"wid","endIndex":8025,"keyWords":5},{"key":"wie","endIndex":8026,"keyWords":1},{"key":"wif","endIndex":8027,"keyWords":1},{"key":"wig","endIndex":8028,"keyWords":1},{"key":"wil","endIndex":8033,"keyWords":5},{"key":"win","endIndex":8045,"keyWords":12},{"key":"wip","endIndex":8046,"keyWords":1},{"key":"wir","endIndex":8048,"keyWords":2},{"key":"wis","endIndex":8053,"keyWords":5},{"key":"wit","endIndex":8061,"keyWords":8},{"key":"wiz","endIndex":8063,"keyWords":2},{"key":"wob","endIndex":8064,"keyWords":1},{"key":"wom","endIndex":8068,"keyWords":4},{"key":"won","endIndex":8070,"keyWords":2},{"key":"woo","endIndex":8076,"keyWords":6},{"key":"wor","endIndex":8098,"keyWords":22},{"key":"wou","endIndex":8099,"keyWords":1},{"key":"wra","endIndex":8103,"keyWords":4},{"key":"wre","endIndex":8111,"keyWords":8},{"key":"wri","endIndex":8120,"keyWords":9},{"key":"wro","endIndex":8121,"keyWords":1},{"key":"wyo","endIndex":8122,"keyWords":1},{"key":"xer","endIndex":8123,"keyWords":1},{"key":"xra","endIndex":8124,"keyWords":1},{"key":"xyl","endIndex":8125,"keyWords":1},{"key":"yac","endIndex":8127,"keyWords":2},{"key":"yan","endIndex":8129,"keyWords":2},{"key":"yar","endIndex":8132,"keyWords":3},{"key":"yaw","endIndex":8133,"keyWords":1},{"key":"yea","endIndex":8139,"keyWords":6},{"key":"yel","endIndex":8142,"keyWords":3},{"key":"yem","endIndex":8143,"keyWords":1},{"key":"yes","endIndex":8144,"keyWords":1},{"key":"yie","endIndex":8145,"keyWords":1},{"key":"yog","endIndex":8146,"keyWords":1},{"key":"yok","endIndex":8147,"keyWords":1},{"key":"yol","endIndex":8148,"keyWords":1},{"key":"yon","endIndex":8149,"keyWords":1},{"key":"you","endIndex":8156,"keyWords":7},{"key":"zai","endIndex":8157,"keyWords":1},{"key":"zam","endIndex":8158,"keyWords":1},{"key":"zea","endIndex":8160,"keyWords":2},{"key":"zeb","endIndex":8161,"keyWords":1},{"key":"zen","endIndex":8162,"keyWords":1},{"key":"zer","endIndex":8163,"keyWords":1},{"key":"zes","endIndex":8164,"keyWords":1},{"key":"zig","endIndex":8165,"keyWords":1},{"key":"zim","endIndex":8166,"keyWords":1},{"key":"zin","endIndex":8167,"keyWords":1},{"key":"zio","endIndex":8170,"keyWords":3},{"key":"zod","endIndex":8171,"keyWords":1},{"key":"zom","endIndex":8172,"keyWords":1},{"key":"zon","endIndex":8173,"keyWords":1},{"key":"zoo","endIndex":8175,"keyWords":2}],"winningWordsLengths":{"4":1037,"5":1375,"6":1659,"7":1554,"8":1409,"9":1141},"easterEggDays":{"01.01":{"type":"yearStart","specialMode":"sandbox-live","emojis":[{"correct":[""],"position":["","","","",""],"incorrect":["",""],"typedKnownIncorrect":["","",""]}]},"14.02":{"type":"valentine","specialMode":"sandbox-live","emojis":[{"correct":[""],"position":[""],"incorrect":[""],"typedKnownIncorrect":[""]}]},"01.04":{"type":"normal","specialMode":"sandbox-live","emojis":[{"correct":[""],"position":[""],"incorrect":[""],"typedKnownIncorrect":[""]}]},"31.12":{"type":"yearEnd","specialMode":"sandbox-live","emojis":[{"correct":[""],"position":["","","","",""],"incorrect":["",""],"typedKnownIncorrect":["","",""]}]}}}