{"soud":1935,"soudce":1957,"soutěž":2542,"soudní":2567,"soukromí":2597,"souhlasit":3637,"souhlas":4309,"soukromý":4646,"soudit":5907,"soused":6688,"soustrast":7115,"soucit":7524,"soubor":8847,"současně":9566,"souladu":10627,"soutěžící":11952,"současný":15134,"sousto":16000,"soupeř":16214,"soudruh":22580,"souhvězdí":23475,"soustava":27551,"soudný":27907,"soužití":28040,"sousední":30785,"soumrak":35299,"souložit":35444,"součet":36565,"souprava":38477,"soulož":41224,"soupis":42675,"soucitný":42833,"soutěžení":47286}