{
	"best": {
		"word": "hilt",
		"letters": 18
	},
	"worst": {
		"word": "electrode",
		"letters": 51
	},
	"totalWords": {
		"2": 2,
		"3": 18,
		"4": 19,
		"5": 10,
		"6": 4,
		"7": 2,
		"8": 1,
		"9": 2
	},
	"totalLetters": {
		"18": 1,
		"19": 5,
		"20": 1,
		"21": 1,
		"22": 4,
		"23": 4,
		"24": 6,
		"25": 6,
		"26": 3,
		"27": 4,
		"28": 3,
		"29": 1,
		"30": 4,
		"31": 2,
		"32": 1,
		"33": 3,
		"34": 1,
		"35": 2,
		"36": 2,
		"39": 1,
		"44": 1,
		"45": 1,
		"51": 1
	},
	"gamesPlayed": 58,
	"medianWords": 3.5,
	"medianLetters": 25.5
}