{"klasy":1853,"kłamstwo":2470,"kłamać":3122,"klasa":4965,"kłamca":7133,"klątwa":8708,"klatka":11495,"klasyczny":12747,"klan":14083,"kłaść":21627,"klasztor":23846,"kłamliwy":27101,"klapa":29473,"klacz":31637,"klawisz":37383,"klamka":38204,"klakson":39805,"klauzula":45119,"klaps":46224,"klapek":66073,"klamra":72803,"klarnet":75857,"kląć":90173,"kładka":127267,"klapka":130556,"klawesyn":162552,"kłąb":177417,"klakier":187606,"klaster":206046,"klamerka":216633,"klaczka":224542,"klaser":318143,"kłamliwie":362561,"klanowy":364672,"klauzura":389423,"klasycyzm":431667,"kłącze":473016}